{
	"buttons": [
		{
			"name": "RNRoundedRect",
			"mode": "momentarily",
			"texture": "ui/rn_uikit.png",
			"insets": {
				"top": 12.0,
				"bottom": 12.0,
				"left": 13.0,
				"right": 13.0
			},
			"contentInsets": {
				"top": 8.0,
				"bottom": 8.0,
				"left": 8.0,
				"right": 8.0
			},
			"states": [
				{
					"name": "normal",
					"atlas": {
						"x": 0.0,
						"y": 0.0,
						"width": 31.0,
						"height": 28.0
					}
				},
				{
					"name": "selected",
					"atlas": {
						"x": 62.0,
						"y": 0.0,
						"width": 31.0,
						"height": 28.0
					}
				},
				{
					"name": "highlighted",
					"atlas": {
						"x": 31.0,
						"y": 0.0,
						"width": 31.0,
						"height": 28.0
					}
				}
			]
		},
		{
			"name": "RNPushButton",
			"mode": "momentarily",
			"texture": "ui/rn_uikit.png",
			"insets": {
				"top": 5.0,
				"bottom": 5.0,
				"left": 5.0,
				"right": 5.0
			},
			"contentInsets": {
				"top": 5.0,
				"bottom": 5.0,
				"left": 5.0,
				"right": 5.0
			},
			"states": [
				{
					"name": "normal",
					"atlas": {
						"x": 93.0,
						"y": 0.0,
						"width": 11.0,
						"height": 28.0
					}
				},
				{
					"name": "selected",
					"atlas": {
						"x": 104.0,
						"y": 0.0,
						"width": 11.0,
						"height": 28.0
					}
				},
				{
					"name": "highlighted",
					"atlas": {
						"x": 115.0,
						"y": 0.0,
						"width": 11.0,
						"height": 28.0
					}
				}
			]
		},
		{
			"name": "RNCheckBox",
			"mode": "switch",
			"texture": "ui/rn_uikit.png",
			"background": false,
			"contentInsets": {
				"top": 0.0,
				"bottom": 0.0,
				"left": 0.0,
				"right": 0.0
			},
			"states": [
				{
					"name": "normal",
					"atlas": {
						"x": 126.0,
						"y": 16.0,
						"width": 15.0,
						"height": 15.0
					}
				},
				{
					"name": "selected",
					"atlas": {
						"x": 126.0,
						"y": 0.0,
						"width": 15.0,
						"height": 15.0
					}
				},
				{
					"name": "highlighted",
					"atlas": {
						"x": 142.0,
						"y": 0.0,
						"width": 15.0,
						"height": 15.0
					}
				}
			]
		},
		{
			"name": "RNDisclosureTriangle",
			"mode": "switch",
			"texture": "ui/rn_uikit.png",
			"background": false,
			"contentInsets": {
				"top": 0.0,
				"bottom": 0.0,
				"left": 0.0,
				"right": 0.0
			},
			"states": [
				{
					"name": "normal",
					"atlas": {
						"x": 169.0,
						"y": 0.0,
						"width": 9.0,
						"height": 9.0
					}
				},
				{
					"name": "selected",
					"atlas": {
						"x": 159.0,
						"y": 0.0,
						"width": 9.0,
						"height": 9.0
					}
				}
			]
		}
	],
	"textfields": [
		{
			"name": "RNRoundedRect",
			"contentInsets": {
				"top": 0.0,
				"bottom": 0.0,
				"left": 5.0,
				"right": 5.0
			},
			"background": {
				"texture": "ui/rn_uikit.png",
				"atlas": {
					"x": 1.0,
					"y": 49.0,
					"width": 27.0,
					"height": 25.0
				},
				"insets": {
					"top": 12.0,
					"bottom": 12.0,
					"left": 13.0,
					"right": 13.0
				}
			}
		},
		{
			"name": "RNBezel",
			"contentInsets": {
				"top": 0.0,
				"bottom": 0.0,
				"left": 5.0,
				"right": 5.0
			},
			"clipInsets": {
				"top": 0.0,
				"bottom": 0.0,
				"left": 2.0,
				"right": 2.0
			},
			"background": {
				"texture": "ui/rn_uikit.png",
				"atlas": {
					"x": 29.0,
					"y": 49.0,
					"width": 10.0,
					"height": 9.0
				},
				"insets": {
					"top": 4.0,
					"bottom": 4.0,
					"left": 4.0,
					"right": 4.0
				}
			}
		}
	]
}